CHANGELOG.md
LICENSE
MANIFEST.in
README.md
requirements.txt
setup.cfg
setup.py
pixelpin_auth_flask_sqlalchemy/__init__.py
pixelpin_auth_flask_sqlalchemy/models.py
pixelpin_auth_flask_sqlalchemy.egg-info/PKG-INFO
pixelpin_auth_flask_sqlalchemy.egg-info/SOURCES.txt
pixelpin_auth_flask_sqlalchemy.egg-info/dependency_links.txt
pixelpin_auth_flask_sqlalchemy.egg-info/not-zip-safe
pixelpin_auth_flask_sqlalchemy.egg-info/requires.txt
pixelpin_auth_flask_sqlalchemy.egg-info/top_level.txt