Metadata-Version: 1.1
Name: pixelpin-auth-flask-sqlalchemy
Version: 1.0.1
Summary: Python Social Authentication, SQLAlchemy Flask models integration.
Home-page: https://github.com/PixelPinPlugins/pixelpin-auth-flask-sqlalchemy
Author: Matias Aguirre, Callum Brankin
Author-email: callum@pixelpin.co.uk
License: BSD
Keywords: flask,sqlalchemy,social auth,pixelpin,pixelpin auth
Platform: UNKNOWN
Classifier: Development Status :: 4 - Beta
Classifier: Topic :: Internet
Classifier: License :: OSI Approved :: BSD License
Classifier: Intended Audience :: Developers
Classifier: Environment :: Web Environment
Classifier: Programming Language :: Python
Classifier: Programming Language :: Python :: 2.7
Classifier: Programming Language :: Python :: 3
